contest_helper/__init__.py
contest_helper/basic.py
contest_helper/exceptions.py
contest_helper/utils.py
contest_helper/values.py
contest_helper/cli/__init__.py
contest_helper/cli/combine.py
contest_helper/cli/compilers.py
contest_helper/cli/make_checker.py
contest_helper/cli/make_postprocessor.py
contest_helper/cli/start_problem.py
contest_helper/cli/statement_preview.py
contest_helper/cli/test.py
contest_helper/cli/utils.py
contest_helper/cli/templates/Makefile
contest_helper/cli/templates/build.sh
contest_helper/cli/templates/check.py
contest_helper/cli/templates/checker.py
contest_helper/cli/templates/compilers.csv
contest_helper/cli/templates/generator.py
contest_helper/cli/templates/meta.json
contest_helper/cli/templates/postprocessor.py
contest_helper/cli/templates/samples/en.md
contest_helper/cli/templates/samples/ru.md
contest_helper/cli/templates/statements/en.md
contest_helper/cli/templates/statements/ru.md
contest_helper/extra/__init__.py
contest_helper/extra/datetime.py
contest_helper/extra/db.py
contest_helper-0.6.10.dist-info/licenses/LICENSE
contest_helper-0.6.10.dist-info/METADATA
contest_helper-0.6.10.dist-info/WHEEL
contest_helper-0.6.10.dist-info/entry_points.txt
contest_helper-0.6.10.dist-info/top_level.txt
contest_helper-0.6.10.dist-info/RECORD
