Metadata-Version: 2.4
Name: contest-helper
Version: 0.6.10
Summary: A flexible framework for generating randomized test cases with input/output validation, designed for competitive programming and algorithmic testing.
Home-page: https://github.com/kirillcskaslezin/contest-helper
Author: Kirill cSKA Slezin
Author-email: kirill.cska.slezin@gmail.com
Classifier: Programming Language :: Python :: 3
Classifier: License :: OSI Approved :: MIT License
Classifier: Operating System :: OS Independent
Requires-Python: >=3.10
License-File: LICENSE
Requires-Dist: tabulate>=0.9.0
Dynamic: license-file
